odoo8_addon_information_security_manual-8.0.1.0.0-py2.7-nspkg.pth
odoo_addons/information_security_manual/__openerp__.py
odoo_addons/information_security_manual/__init__.py
odoo_addons/information_security_manual/data/document_page.xml
odoo_addons/information_security_manual/static/description/icon.png
odoo8_addon_information_security_manual-8.0.1.0.0.dist-info/top_level.txt
odoo8_addon_information_security_manual-8.0.1.0.0.dist-info/WHEEL
odoo8_addon_information_security_manual-8.0.1.0.0.dist-info/RECORD
odoo8_addon_information_security_manual-8.0.1.0.0.dist-info/metadata.json
odoo8_addon_information_security_manual-8.0.1.0.0.dist-info/DESCRIPTION.rst
odoo8_addon_information_security_manual-8.0.1.0.0.dist-info/METADATA
odoo8_addon_information_security_manual-8.0.1.0.0.dist-info/namespace_packages.txt
